setup.py
cloudwatchmon/__init__.py
cloudwatchmon/cloud_watch_client.py
cloudwatchmon.egg-info/PKG-INFO
cloudwatchmon.egg-info/SOURCES.txt
cloudwatchmon.egg-info/dependency_links.txt
cloudwatchmon.egg-info/entry_points.txt
cloudwatchmon.egg-info/requires.txt
cloudwatchmon.egg-info/top_level.txt
cloudwatchmon.egg-info/zip-safe
cloudwatchmon/cli/__init__.py
cloudwatchmon/cli/get_instance_stats.py
cloudwatchmon/cli/put_instance_stats.py