Metadata-Version: 1.1
Name: cloudwatchmon
Version: 2.0.2
Summary: Linux monitoring scripts for CloudWatch
Home-page: https://github.com/osiegmar/cloudwatch-mon-scripts-python
Author: Oliver Siegmar
Author-email: oliver@siegmar.net
License: Apache License (2.0)
Keywords: monitoring cloudwatch amazon web services aws ec2
Platform: UNKNOWN
Classifier: License :: OSI Approved :: Apache Software License
Classifier: Topic :: System :: Monitoring
